Workbook

Sheet Порівняння
A1: Статус | B1: Що сталось | C1: Мій ID | D1: Мій товар | E1: Моя ціна, грн | F1: У мене в наявності | G1: Водоспад: ціна, грн | H1: Водоспад: наявність | I1: Клуб Рослин: ціна, грн | J1: Клуб Рослин: наявність | K1: Орієнтир | L1: Ціна орієнтира, грн | M1: Різниця, грн | N1: Різниця, % | O1: Зміна в орієнтира сьогодні, грн | P1: Змін в орієнтира за 30 днів | Q1: Розбіжність, днів | R1: Як зіставлено | S1: Мій товар
A2: Потребує уваги | B2: Ваша ціна нижча на 5150 грн (90.5%) | C2: 123100400 | D2: Точильний камінь 4000/1000 S&R (123100400) Німеччина | E2: 540 | F2: так | G2: 5690 | H2: так | K2: Водоспад | L2: 5690 | M2: =IF(L2="","",E2-L2) | N2: =IF(OR(L2="",L2=0),"",M2/L2) | P2: 0 | Q2: 1 | R2: код | S2: відкрити
A3: Потребує уваги | B3: Ваша ціна нижча на 4935 грн (86.7%) | C3: 123100402 | D3: Набір точильних каменів 120/240 та 4000/1000 гріт S&R (123100402) Німеччина | E3: 755 | F3: так | G3: 5690 | H3: так | K3: Водоспад | L3: 5690 | M3: =IF(L3="","",E3-L3) | N3: =IF(OR(L3="",L3=0),"",M3/L3) | P3: 0 | Q3: 1 | R3: код | S3: відкрити
A4: Потребує уваги | B4: Ваша ціна нижча на 750 грн (46.9%); Немає в наявності в жодного постачальника | C4: SD-95-PN | D4: Точилка діамантова для вигнутих країв АРС / ARS Pen (SD-95-PN) Японія | E4: 849 | F4: так | I4: 1599 | J4: ні | K4: Клуб Рослин | L4: 1599 | M4: =IF(L4="","",E4-L4) | N4: =IF(OR(L4="",L4=0),"",M4/L4) | P4: 0 | Q4: 1 | R4: код | S4: відкрити
A5: Потребує уваги | B5: Ваша ціна нижча на 1557 грн (26.8%) | C5: 0.600.8B2.100 | D5: Секатор Bosch EasyPrune акумуляторний (0.600.8B2.100) Німеччина | E5: 4245 | F5: ні | G5: 5802 | H5: ні | K5: Водоспад | L5: 5802 | M5: =IF(L5="","",E5-L5) | N5: =IF(OR(L5="",L5=0),"",M5/L5) | P5: 0 | Q5: 1 | R5: код | S5: відкрити
A6: Потребує уваги | B6: Ваша ціна нижча на 549 грн (19.6%) | C6: 7249 | D6: Добриво Преміум Фоліар Premium Foliar 19-19-19+ТЕ 15 кг AgroWork Туреччина | E6: 2250 | F6: ні | I6: 2799 | J6: ні | K6: Клуб Рослин | L6: 2799 | M6: =IF(L6="","",E6-L6) | N6: =IF(OR(L6="",L6=0),"",M6/L6) | P6: 0 | Q6: 1 | R6: код | S6: відкрити
A7: Потребує уваги | B7: Ваша ціна нижча на 33 грн (18.5%) | C7: 120500200101 | D7: Маркер перманентний Baumschulen чорний 2 мм (120500200101) Німеччина | E7: 145 | F7: ні | I7: 178 | J7: так | K7: Клуб Рослин | L7: 178 | M7: =IF(L7="","",E7-L7) | N7: =IF(OR(L7="",L7=0),"",M7/L7) | P7: 0 | Q7: 1 | R7: код | S7: відкрити
A8: Потребує уваги | B8: Ваша ціна нижча на 430 грн (16.6%) | C8: P57-25-F | D8: Кущоріз Bahco P57-25-F Бахо | E8: 2160 | F8: так | G8: 2590 | H8: так | K8: Водоспад | L8: 2590 | M8: =IF(L8="","",E8-L8) | N8: =IF(OR(L8="",L8=0),"",M8/L8) | P8: 0 | Q8: 1 | R8: код | S8: відкрити
A9: Потребує уваги | B9: Ваша ціна нижча на 450 грн (15.3%) | C9: PX-M3-R500P | D9: Секатор Bahco PX-M3 для обрізки саду | E9: 2500 | F9: ні | G9: 2050 | H9: ні | I9: 2950 | J9: так | K9: Клуб Рослин | L9: 2950 | M9: =IF(L9="","",E9-L9) | N9: =IF(OR(L9="",L9=0),"",M9/L9) | P9: 0 | Q9: 1 | R9: назва | S9: відкрити
A10: Потребує уваги | B10: Ваша ціна нижча на 100 грн (12.5%) | C10: 11827 | D10: Ніж Morakniv Companion MG Olive (11827) Mora Швеція | E10: 699 | F10: так | G10: 799 | H10: так | K10: Водоспад | L10: 799 | M10: =IF(L10="","",E10-L10) | N10: =IF(OR(L10="",L10=0),"",M10/L10) | P10: 0 | Q10: 1 | R10: код | S10: відкрити
A11: Потребує уваги | B11: Ваша ціна нижча на 22 грн (10.0%) | C11: Rain1 | D11: Опадомір (дощомір) пластиковий 0-50 mm L/m2 (Rain1) Corteva | E11: 198 | F11: ні | G11: 220 | H11: ні | K11: Водоспад | L11: 220 | M11: =IF(L11="","",E11-L11) | N11: =IF(OR(L11="",L11=0),"",M11/L11) | P11: 0 | Q11: 1 | R11: код | S11: відкрити
A12: Потребує уваги | B12: Ваша ціна нижча на 1474 грн (8.7%) | C12: BCL20IB | D12: Секатор акумуляторний Bahco BCL20IB Бахо | E12: 15525 | F12: ні | G12: 16999 | H12: ні | K12: Водоспад | L12: 16999 | M12: =IF(L12="","",E12-L12) | N12: =IF(OR(L12="",L12=0),"",M12/L12) | P12: 0 | Q12: 1 | R12: код | S12: відкрити
A13: Потребує уваги | B13: Ваша ціна нижча на 141 грн (8.3%) | C13: UV-32Е | D13: Пила АРС / ARS (UV-32E) серповидна з кобурою Японія | E13: 1549 | F13: ні | G13: 1690 | H13: так | K13: Водоспад | L13: 1690 | M13: =IF(L13="","",E13-L13) | N13: =IF(OR(L13="",L13=0),"",M13/L13) | P13: 0 | Q13: 1 | R13: код | S13: відкрити
A14: Потребує уваги | B14: Ваша ціна нижча на 40 грн (7.7%) | C14: 120500100606 | D14: Етикетки на дроті білі ПВХ 2.0 х 10 см 250 шт Німеччина | E14: 479 | F14: ні | I14: 519 | J14: так | K14: Клуб Рослин | L14: 519 | M14: =IF(L14="","",E14-L14) | N14: =IF(OR(L14="",L14=0),"",M14/L14) | P14: 0 | Q14: 1 | R14: код | S14: відкрити
A15: Потребує уваги | B15: Ваша ціна нижча на 55 грн (7.6%) | C15: 120500100703 | D15: Етикетки-кілочки для рослин PET-R білі 1.6 х 10 см 500 шт | E15: 670 | F15: ні | I15: 725 | J15: так | K15: Клуб Рослин | L15: 725 | M15: =IF(L15="","",E15-L15) | N15: =IF(OR(L15="",L15=0),"",M15/L15) | P15: 0 | Q15: 1 | R15: код | S15: відкрити
A16: Потребує уваги | B16: Ваша ціна нижча на 405 грн (7.5%) | C16: KST 231 | D16: Садові ножиці для живоплоту Окатсуне / Okatsune (KST 231) Японія | E16: 4985 | F16: так | G16: 5390 | H16: так | I16: 5390 | J16: так | K16: Водоспад | L16: 5390 | M16: =IF(L16="","",E16-L16) | N16: =IF(OR(L16="",L16=0),"",M16/L16) | P16: 0 | Q16: 1 | R16: код | S16: відкрити
A17: Потребує уваги | B17: Ваша ціна нижча на 13 грн (7.3%) | C17: 120500200110 | D17: Маркер перманентний Edding 400 чорний 1.0 мм Німеччина | E17: 165 | F17: ні | I17: 178 | J17: так | K17: Клуб Рослин | L17: 178 | M17: =IF(L17="","",E17-L17) | N17: =IF(OR(L17="",L17=0),"",M17/L17) | P17: 0 | Q17: 1 | R17: код | S17: відкрити
A18: Потребує уваги | B18: Ваша ціна нижча на 14 грн (7.0%) | C18: 120500200103 | D18: Маркер перманентний Pancolor Lumocolor 303F червоний 0.6 мм Staedtler Німеччина | E18: 186 | F18: ні | I18: 200 | J18: так | K18: Клуб Рослин | L18: 200 | M18: =IF(L18="","",E18-L18) | N18: =IF(OR(L18="",L18=0),"",M18/L18) | P18: 0 | Q18: 1 | R18: код | S18: відкрити
A19: Потребує уваги | B19: Ваша ціна нижча на 14 грн (7.0%) | C19: 120500200104 | D19: Маркер перманентний Pancolor Lumocolor 303M чорний 1.0 мм (120500200104) Staedtler Німеччина | E19: 186 | F19: ні | I19: 200 | J19: так | K19: Клуб Рослин | L19: 200 | M19: =IF(L19="","",E19-L19) | N19: =IF(OR(L19="",L19=0),"",M19/L19) | P19: 0 | Q19: 1 | R19: код | S19: відкрити
A20: Потребує уваги | B20: Ваша ціна нижча на 36 грн (6.7%) | C20: P127-19 | D20: Ножиці для збору врожаю P127-19 Bahco | E20: 504 | F20: так | I20: 540 | J20: так | K20: Клуб Рослин | L20: 540 | M20: =IF(L20="","",E20-L20) | N20: =IF(OR(L20="",L20=0),"",M20/L20) | P20: 0 | Q20: 1 | R20: код | S20: відкрити
A21: Потребує уваги | B21: Ваша ціна нижча на 300 грн (6.7%) | C21: 5386 | D21: Садові ножиці для кущів Окатсуне / Okatsune (KST 216) | E21: 4190 | F21: ні | G21: 4490 | H21: так | I21: 4490 | J21: так | K21: Водоспад | L21: 4490 | M21: =IF(L21="","",E21-L21) | N21: =IF(OR(L21="",L21=0),"",M21/L21) | P21: 0 | Q21: 1 | R21: код
A22: Потребує уваги | B22: Ваша ціна нижча на 300 грн (6.7%) | C22: KST 216 | D22: Садові ножиці для кущів Окатсуне / Okatsune (KST216) Японія | E22: 4190 | F22: ні | G22: 4490 | H22: так | I22: 4490 | J22: так | K22: Водоспад | L22: 4490 | M22: =IF(L22="","",E22-L22) | N22: =IF(OR(L22="",L22=0),"",M22/L22) | P22: 0 | Q22: 1 | R22: код | S22: відкрити
A23: Потребує уваги | B23: Ваша ціна нижча на 139 грн (6.5%) | C23: 2C 380/20 | D23: Секатор Due Cigni 200 мм (2C 380/20) Італія | E23: 1990 | F23: ні | G23: 2129 | H23: так | K23: Водоспад | L23: 2129 | M23: =IF(L23="","",E23-L23) | N23: =IF(OR(L23="",L23=0),"",M23/L23) | P23: 0 | Q23: 1 | R23: код | S23: відкрити
A24: Потребує уваги | B24: Ваша ціна нижча на 53 грн (4.9%) | C24: R260A | D24: Запасне опорне лезо для сучкоріза Bahco P-160 R260A | E24: 1037 | F24: так | G24: 1090 | H24: так | I24: 1090 | J24: так | K24: Водоспад | L24: 1090 | M24: =IF(L24="","",E24-L24) | N24: =IF(OR(L24="",L24=0),"",M24/L24) | P24: 0 | Q24: 1 | R24: код | S24: відкрити
A25: Потребує уваги | B25: Ваша ціна нижча на 5 грн (4.8%) | C25: 23FCSPE12 | D25: Підв`язка для рослин 12 см Х 1000 шт гнучкий сталевий дріт у паперовій оболонці (23FCSPE12) Італія | E25: 100 | F25: так | G25: 105 | H25: так | K25: Водоспад | L25: 105 | M25: =IF(L25="","",E25-L25) | N25: =IF(OR(L25="",L25=0),"",M25/L25) | P25: 0 | Q25: 1 | R25: код | S25: відкрити
A26: Потребує уваги | B26: Ваша ціна нижча на 60 грн (4.8%) | C26: KST404 | D26: Серп садовий Окатсуне / Okatsune (KST 404) Японія | E26: 1190 | F26: так | G26: 1250 | H26: так | I26: 1190 | J26: ні | K26: Водоспад | L26: 1250 | M26: =IF(L26="","",E26-L26) | N26: =IF(OR(L26="",L26=0),"",M26/L26) | P26: 0 | Q26: 1 | R26: код | S26: відкрити
A27: Потребує уваги | B27: Ваша ціна нижча на 15 грн (4.3%) | C27: 23FIPEGRVS3 | D27: Агротрубка (кембрик) для підв`язки рослин 3 мм 1 кг 230 м Super extra cordioli (23FIPEGRVS3) Італія | E27: 330 | F27: так | G27: 345 | H27: так | K27: Водоспад | L27: 345 | M27: =IF(L27="","",E27-L27) | N27: =IF(OR(L27="",L27=0),"",M27/L27) | P27: 0 | Q27: 1 | R27: код | S27: відкрити
A28: Потребує уваги | B28: Ваша ціна нижча на 200 грн (4.3%) | C28: Lopata_M | D28: Лопата саперна Нівакі / Niwaki 820x160x28 мм 0.98 кг (Lopata_M) Японія | E28: 4399 | F28: ні | G28: 4599 | H28: ні | K28: Водоспад | L28: 4599 | M28: =IF(L28="","",E28-L28) | N28: =IF(OR(L28="",L28=0),"",M28/L28) | P28: 0 | Q28: 1 | R28: код | S28: відкрити
A29: Потребує уваги | B29: Ваша ціна нижча на 40 грн (4.0%) | C29: KST108 | D29: Чохол шкіряний Окатсуне / Okatsune (KST108) Японія | E29: 950 | F29: так | G29: 990 | H29: так | I29: 890 | J29: ні | K29: Водоспад | L29: 990 | M29: =IF(L29="","",E29-L29) | N29: =IF(OR(L29="",L29=0),"",M29/L29) | P29: 0 | Q29: 1 | R29: код | S29: відкрити
A30: Потребує уваги | B30: Ваша ціна нижча на 51 грн (3.9%) | C30: 6b06622a-abbb-11ee-bf43-c87f546feb15 | D30: Лопата штикова Bellota 3103 MFVA.B Іспанія | E30: 1259 | F30: ні | I30: 1310 | J30: так | K30: Клуб Рослин | L30: 1310 | M30: =IF(L30="","",E30-L30) | N30: =IF(OR(L30="",L30=0),"",M30/L30) | P30: 0 | Q30: 1 | R30: схожа назва
A31: Потребує уваги | B31: Ваша ціна нижча на 180 грн (3.8%) | C31: 7d31f229-bf5c-11ee-bf58-c87f546feb15 | D31: Коса 660 мм Bellota 2509-26.B Іспанія | E31: 4499 | F31: ні | I31: 4679 | J31: так | K31: Клуб Рослин | L31: 4679 | M31: =IF(L31="","",E31-L31) | N31: =IF(OR(L31="",L31=0),"",M31/L31) | P31: 0 | Q31: 1 | R31: код
A32: Потребує уваги | B32: Ваша ціна нижча на 42 грн (3.5%) | C32: R185V | D32: Запасне лезо для гілкоріза Bahco P280 (R185V) | E32: 1148 | F32: так | G32: 1190 | H32: так | K32: Водоспад | L32: 1190 | M32: =IF(L32="","",E32-L32) | N32: =IF(OR(L32="",L32=0),"",M32/L32) | P32: 0 | Q32: 1 | R32: код | S32: відкрити
A33: Потребує уваги | B33: Ваша ціна нижча на 90 грн (3.0%) | C33: 446-24 | D33: Садова пила складна Silky Ultra Accel Curve 240-7.5 (446-24) Японія | E33: 2900 | F33: ні | G33: 2990 | H33: так | K33: Водоспад | L33: 2990 | M33: =IF(L33="","",E33-L33) | N33: =IF(OR(L33="",L33=0),"",M33/L33) | P33: 0 | Q33: 1 | R33: код | S33: відкрити
A34: Потребує уваги | B34: Ваша ціна нижча на 10 грн (2.9%) | C34: 23FIPEGRVS2 | D34: Агротрубка (кембрик) для підв`язки рослин 2 мм 1кг 320 м Super extra cordioli (23FIPEGRVS2) Італія | E34: 340 | F34: так | G34: 350 | H34: так | K34: Водоспад | L34: 350 | M34: =IF(L34="","",E34-L34) | N34: =IF(OR(L34="",L34=0),"",M34/L34) | P34: 0 | Q34: 1 | R34: код | S34: відкрити
A35: Потребує уваги | B35: Ваша ціна нижча на 10 грн (2.8%) | C35: 23FIPEGRVS6 | D35: Агротрубка (кембрик) для підв`язки рослин 6 мм 1 кг 98 м Super extra cordioli (23FIPEGRVS6) Італія | E35: 350 | F35: так | G35: 360 | H35: так | K35: Водоспад | L35: 360 | M35: =IF(L35="","",E35-L35) | N35: =IF(OR(L35="",L35=0),"",M35/L35) | P35: 0 | Q35: 1 | R35: код | S35: відкрити
A36: Потребує уваги | B36: Ваша ціна нижча на 40 грн (2.8%) | C36: LAP-KNIFE | D36: Набір Bahco laplander 396 пилка + Knife 2446 ніж (LAP-KNIFE) | E36: 1390 | F36: так | G36: 1430 | H36: так | K36: Водоспад | L36: 1430 | M36: =IF(L36="","",E36-L36) | N36: =IF(OR(L36="",L36=0),"",M36/L36) | P36: 0 | Q36: 1 | R36: назва | S36: відкрити
A37: Потребує уваги | B37: Ваша ціна нижча на 10 грн (2.2%) | C37: 121000332326 | D37: Масло камелии антикоррозионное Kurobara Tsubak 100 млi Hanakumagawa Япония | E37: 445 | F37: ні | I37: 455 | J37: так | K37: Клуб Рослин | L37: 455 | M37: =IF(L37="","",E37-L37) | N37: =IF(OR(L37="",L37=0),"",M37/L37) | P37: 0 | Q37: 1 | R37: код
A38: Потребує уваги | B38: Ваша ціна нижча на 42 грн (1.9%) | C38: P34-27A-F | D38: Висоторіз Bahco P34-27A-F | E38: 2148 | F38: так | G38: 2190 | H38: так | I38: 2190 | J38: так | K38: Водоспад | L38: 2190 | M38: =IF(L38="","",E38-L38) | N38: =IF(OR(L38="",L38=0),"",M38/L38) | P38: 0 | Q38: 1 | R38: код | S38: відкрити
A39: Потребує уваги | B39: Ваша ціна нижча на 5 грн (1.5%) | C39: 5170007N | D39: Віск для щеплення червоний гранульований з фунгіцидами Plastigreffe 6535 - 500 г (5170007N) AgriChem Італія | E39: 320 | F39: так | G39: 325 | H39: так | K39: Водоспад | L39: 325 | M39: =IF(L39="","",E39-L39) | N39: =IF(OR(L39="",L39=0),"",M39/L39) | P39: 0 | Q39: 1 | R39: код | S39: відкрити
A40: Потребує уваги | B40: Ваша ціна нижча на 60 грн (1.5%) | C40: P160-SL-75 | D40: Гілкоріз Bahco P160-SL-75 | E40: 3990 | F40: так | G40: 4050 | H40: так | I40: 4050 | J40: так | K40: Водоспад | L40: 4050 | M40: =IF(L40="","",E40-L40) | N40: =IF(OR(L40="",L40=0),"",M40/L40) | P40: 0 | Q40: 1 | R40: код | S40: відкрити
A41: Потребує уваги | B41: Ваша ціна нижча на 5 грн (1.4%); Немає в наявності в жодного постачальника | C41: 23FIPEGRVS4 | D41: Агротрубка (кембрик) для підв`язки рослин 4 мм 1 кг 160 м Super extra Cordioli (23FIPEGRVS4) Італія | E41: 340 | F41: так | G41: 345 | H41: ні | K41: Водоспад | L41: 345 | M41: =IF(L41="","",E41-L41) | N41: =IF(OR(L41="",L41=0),"",M41/L41) | P41: 0 | Q41: 1 | R41: код | S41: відкрити
A42: Потребує уваги | B42: Ваша ціна нижча на 5 грн (1.4%) | C42: 23FIPEGRVS5 | D42: Агротрубка (кембрик) для підв`язки рослин 5 мм 1 кг 120 м Super extra cordioli (23FIPEGRVS5) Італія | E42: 340 | F42: так | G42: 345 | H42: так | K42: Водоспад | L42: 345 | M42: =IF(L42="","",E42-L42) | N42: =IF(OR(L42="",L42=0),"",M42/L42) | P42: 0 | Q42: 1 | R42: код | S42: відкрити
A43: Потребує уваги | B43: Ваша ціна нижча на 5 грн (1.4%) | C43: R144PV | D43: Центральний болт і гайка до сучкоріза Bahco P-160 R144PV | E43: 345 | F43: так | G43: 350 | H43: так | K43: Водоспад | L43: 350 | M43: =IF(L43="","",E43-L43) | N43: =IF(OR(L43="",L43=0),"",M43/L43) | P43: 0 | Q43: 1 | R43: код | S43: відкрити
A44: Потребує уваги | B44: Ваша ціна нижча на 4 грн (1.3%) | C44: 5070007N | D44: Віск для щеплення троянд Plastifina 5470 - 900 г (5070007N) AgriChem Італія | E44: 295 | F44: ні | G44: 299 | H44: ні | K44: Водоспад | L44: 299 | M44: =IF(L44="","",E44-L44) | N44: =IF(OR(L44="",L44=0),"",M44/L44) | P44: 0 | Q44: 1 | R44: код | S44: відкрити
A45: Потребує уваги | B45: Ваша ціна нижча на 10 грн (1.2%); Немає в наявності в жодного постачальника | C45: 97004.A | D45: Чохол шкіряний для секатора професійний Алтуна / Altuna (97004.A) Іспанія | E45: 859 | F45: так | G45: 869 | H45: ні | K45: Водоспад | L45: 869 | M45: =IF(L45="","",E45-L45) | N45: =IF(OR(L45="",L45=0),"",M45/L45) | P45: 0 | Q45: 1 | R45: код | S45: відкрити
A46: Потребує уваги | B46: Ваша ціна нижча на 29 грн (0.7%) | C46: 7245 | D46: Добриво Терафлекс Terraflex (17-17-17+TE) 25 кг SmartGrow Бельгія | E46: 3850 | F46: ні | I46: 3879 | J46: ні | K46: Клуб Рослин | L46: 3879 | M46: =IF(L46="","",E46-L46) | N46: =IF(OR(L46="",L46=0),"",M46/L46) | P46: 0 | Q46: 1 | R46: код
A47: Потребує уваги | B47: Ваша ціна нижча на 15 грн (0.6%) | C47: NJP811 | D47: Ніж Rikugatana S нержавіюча сталь DSR1K6 DAIDO Нісаку / Nisaku (NJP811) Японія | E47: 2475 | F47: ні | G47: 2490 | H47: ні | K47: Водоспад | L47: 2490 | M47: =IF(L47="","",E47-L47) | N47: =IF(OR(L47="",L47=0),"",M47/L47) | P47: 0 | Q47: 1 | R47: код | S47: відкрити
A48: Потребує уваги | B48: Ваша ціна нижча на 4 грн (0.4%) | C48: 1001580 | D48: Лопата совкова Fiskars ErgoComfort 132911 (1001580) Фінляндія | E48: 1095 | F48: ні | G48: 1099 | H48: ні | K48: Водоспад | L48: 1099 | M48: =IF(L48="","",E48-L48) | N48: =IF(OR(L48="",L48=0),"",M48/L48) | P48: 0 | Q48: 1 | R48: код | S48: відкрити
A49: Потребує уваги | B49: Ваша ціна нижча на 10 грн (0.4%) | C49: 202P-SP-OT-CH | D49: Щеплювальний ніж з відділювачем кори Due Buoi 202P-SP-OT-CH Італія | E49: 2240 | F49: так | G49: 2250 | H49: так | K49: Водоспад | L49: 2250 | M49: =IF(L49="","",E49-L49) | N49: =IF(OR(L49="",L49=0),"",M49/L49) | P49: 0 | Q49: 1 | R49: код | S49: відкрити
A50: Потребує уваги | B50: Ваша ціна нижча на 4 грн (0.3%) | C50: 2720006N | D50: Паста Арборпласт / Arborplast 5 кг для гарячого щеплення AgriChem Італія | E50: 1295 | F50: ні | G50: 1299 | H50: ні | K50: Водоспад | L50: 1299 | M50: =IF(L50="","",E50-L50) | N50: =IF(OR(L50="",L50=0),"",M50/L50) | P50: 0 | Q50: 1 | R50: код | S50: відкрити
A51: Потребує уваги | B51: Ваша ціна нижча на 3 грн (0.3%) | C51: 120EU | D51: Секатор АРС / ARS (120EU) садовий обвідний Японія | E51: 1176 | F51: ні | I51: 1179 | J51: ні | K51: Клуб Рослин | L51: 1179 | M51: =IF(L51="","",E51-L51) | N51: =IF(OR(L51="",L51=0),"",M51/L51) | P51: 0 | Q51: 1 | R51: модель | S51: відкрити
A52: Потребує уваги | B52: Ваша ціна нижча на 4 грн (0.2%) | C52: 1001567 | D52: Лопата штикова з телескопічною ручкою Fiskars Фіскарс SmartFit (1001567) Фінляндія | E52: 2195 | F52: ні | G52: 2199 | H52: ні | K52: Водоспад | L52: 2199 | M52: =IF(L52="","",E52-L52) | N52: =IF(OR(L52="",L52=0),"",M52/L52) | P52: 0 | Q52: 1 | R52: код
A53: Ваша ціна вища | B53: Ваша ціна вища на 4967 грн (2790.4%) | C53: 160ZF-3.0-5 | D53: Секатор АРС / ARS (160ZF-3.0-5) телескопічний на штанзі 1.8–3 м Японія | E53: 5145 | F53: ні | G53: 5145 | H53: ні | I53: 178 | J53: так | K53: Клуб Рослин | L53: 178 | M53: =IF(L53="","",E53-L53) | N53: =IF(OR(L53="",L53=0),"",M53/L53) | P53: 0 | Q53: 1 | R53: код | S53: відкрити
A54: Ваша ціна вища | B54: Ваша ціна вища на 4692 грн (2636.0%) | C54: 160ZF-2.0-3 | D54: Секатор АРС / ARS (160ZF-2.0-3) телескопічний на штанзі 1.2–2 м Японія | E54: 4870 | F54: ні | G54: 4870 | H54: так | I54: 178 | J54: так | K54: Клуб Рослин | L54: 178 | M54: =IF(L54="","",E54-L54) | N54: =IF(OR(L54="",L54=0),"",M54/L54) | P54: 0 | Q54: 1 | R54: код | S54: відкрити
A55: Ваша ціна вища | B55: Ваша ціна вища на 4271.8 грн (587.4%) | C55: 1003621 | D55: Великий сікач для сучків Фіскарс / Fiskars WoodXpert XA3 126005 (1003621) Фінляндія | E55: 4999 | F55: ні | G55: 3099 | H55: ні | I55: 727.2 | J55: ні | K55: Клуб Рослин | L55: 727.2 | M55: =IF(L55="","",E55-L55) | N55: =IF(OR(L55="",L55=0),"",M55/L55) | P55: 0 | Q55: 1 | R55: код | S55: відкрити
A56: Ваша ціна вища | B56: Ваша ціна вища на 865 грн (259.0%); Немає в наявності в жодного постачальника | C56: 1001622 | D56: Ніж універсальний Фіскарс Fiskars з чохлом K40 125860 (1001622) Фінляндія | E56: 1199 | F56: так | G56: 699 | H56: ні | I56: 334 | J56: ні | K56: Клуб Рослин | L56: 334 | M56: =IF(L56="","",E56-L56) | N56: =IF(OR(L56="",L56=0),"",M56/L56) | P56: 0 | Q56: 1 | R56: код | S56: відкрити
A57: Ваша ціна вища | B57: Ваша ціна вища на 3565.1 грн (248.6%) | C57: 1003623 | D57: Багор великий Фіскарс Fiskars WoodXpert XA22 126007 (1003623) Фінляндія | E57: 4999 | F57: ні | G57: 3099 | H57: ні | I57: 1433.9 | J57: ні | K57: Клуб Рослин | L57: 1433.9 | M57: =IF(L57="","",E57-L57) | N57: =IF(OR(L57="",L57=0),"",M57/L57) | P57: 0 | Q57: 1 | R57: код | S57: відкрити
A58: Ваша ціна вища | B58: Ваша ціна вища на 2703.4 грн (180.8%); Немає в наявності в жодного постачальника | C58: 1001620 | D58: Пила ручна Фіскарс Fiskars SW84 123840 (1001620) Фінляндія | E58: 4199 | F58: так | G58: 2499 | H58: ні | I58: 1495.6 | J58: ні | K58: Клуб Рослин | L58: 1495.6 | M58: =IF(L58="","",E58-L58) | N58: =IF(OR(L58="",L58=0),"",M58/L58) | P58: 0 | Q58: 1 | R58: код | S58: відкрити
A59: Ваша ціна вища | B59: Ваша ціна вища на 1152.9 грн (178.4%); Немає в наявності в жодного постачальника | C59: 1001534 | D59: Секатор площинний Фіскарс Fiskars FingerLoop P44 111440 (1001534) Фінляндія | E59: 1799 | F59: так | G59: 999 | H59: ні | I59: 646.1 | J59: ні | K59: Клуб Рослин | L59: 646.1 | M59: =IF(L59="","",E59-L59) | N59: =IF(OR(L59="",L59=0),"",M59/L59) | P59: 0 | Q59: 1 | R59: код | S59: відкрити
A60: Ваша ціна вища | B60: Ваша ціна вища на 720.7 грн (168.3%) | C60: 1001623 | D60: Ніж зігнутий для щеплень Фіскарс Fiskars K62 125880 (1001623) Фінляндія | E60: 1149 | F60: ні | G60: 749 | H60: ні | I60: 428.3 | J60: ні | K60: Клуб Рослин | L60: 428.3 | M60: =IF(L60="","",E60-L60) | N60: =IF(OR(L60="",L60=0),"",M60/L60) | P60: 0 | Q60: 1 | R60: код | S60: відкрити
A61: Ваша ціна вища | B61: Ваша ціна вища на 853 грн (165.3%); Немає в наявності в жодного постачальника | C61: 1001640 | D61: Комплект по догляду за інвентарем Фіскарс Fiskars 110990 (1001640) Фінляндія | E61: 1369 | F61: так | G61: 899 | H61: ні | I61: 516 | J61: ні | K61: Клуб Рослин | L61: 516 | M61: =IF(L61="","",E61-L61) | N61: =IF(OR(L61="",L61=0),"",M61/L61) | P61: 0 | Q61: 1 | R61: код | S61: відкрити
A62: Ваша ціна вища | B62: Ваша ціна вища на 4199.9 грн (161.6%); Немає в наявності в жодного постачальника | C62: 1001557 | D62: Висоторіз площинний Fiskars UP84 115390 (1001557) Фінляндія | E62: 6799 | F62: так | G62: 4699 | H62: ні | I62: 2599.1 | J62: ні | K62: Клуб Рослин | L62: 2599.1 | M62: =IF(L62="","",E62-L62) | N62: =IF(OR(L62="",L62=0),"",M62/L62) | P62: 0 | Q62: 1 | R62: код | S62: відкрити
A63: Ваша ціна вища | B63: Ваша ціна вища на 1821 грн (161.4%) | C63: 1001410 | D63: Висоторіз Фіскарс Fiskars QuikFit 136525 (1001410) Фінляндія | E63: 2949 | F63: ні | G63: 1999 | H63: ні | I63: 1128 | J63: ні | K63: Клуб Рослин | L63: 1128 | M63: =IF(L63="","",E63-L63) | N63: =IF(OR(L63="",L63=0),"",M63/L63) | P63: 0 | Q63: 1 | R63: код | S63: відкрити
A64: Ваша ціна вища | B64: Ваша ціна вища на 715 грн (160.7%) | C64: R660V | D64: Запасні частини для сучкоріза (Болт і гайка для ручок) Bahco P160 ( R660V ) | E64: 1160 | F64: так | G64: 445 | H64: так | K64: Водоспад | L64: 445 | M64: =IF(L64="","",E64-L64) | N64: =IF(OR(L64="",L64=0),"",M64/L64) | P64: 0 | Q64: 1 | R64: код | S64: відкрити
A65: Ваша ціна вища | B65: Ваша ціна вища на 1781 грн (159.3%); Немає в наявності в жодного постачальника | C65: 1001430 | D65: Гілкоріз великий Фіскарс Fiskars SingleStep (L) L39 112450 (1001430) Фінляндія | E65: 2899 | F65: так | G65: 1599 | H65: ні | I65: 1118 | J65: ні | K65: Клуб Рослин | L65: 1118 | M65: =IF(L65="","",E65-L65) | N65: =IF(OR(L65="",L65=0),"",M65/L65) | P65: 0 | Q65: 1 | R65: код | S65: відкрити
A66: Ваша ціна вища | B66: Ваша ціна вища на 1398.5 грн (159.2%); Немає в наявності в жодного постачальника | C66: 1000612 | D66: Пила висувна Фіскарс / Fiskars Xtract SW72 123860 (1000612) Фінляндія | E66: 2277 | F66: так | G66: 1399 | H66: ні | I66: 878.5 | J66: ні | K66: Клуб Рослин | L66: 878.5 | M66: =IF(L66="","",E66-L66) | N66: =IF(OR(L66="",L66=0),"",M66/L66) | P66: 0 | Q66: 1 | R66: код | S66: відкрити
A67: Ваша ціна вища | B67: Ваша ціна вища на 918.21 грн (158.1%) | C67: 1016036 | D67: Садові граблі Фіскарс Fiskars Solid 135715 (1016036) Фінляндія | E67: 1499 | F67: ні | G67: 899 | H67: ні | I67: 580.79 | J67: ні | K67: Клуб Рослин | L67: 580.79 | M67: =IF(L67="","",E67-L67) | N67: =IF(OR(L67="",L67=0),"",M67/L67) | P67: 0 | Q67: 1 | R67: код | S67: відкрити
A68: Ваша ціна вища | B68: Ваша ціна вища на 1830.1 грн (156.6%) | C68: 1001555 | D68: Гілкоріз малий площинний Фіскарс / Fiskars PowerGear (S) L72 112200 (1001555) Фінляндія | E68: 2999 | F68: ні | G68: 1799 | H68: ні | I68: 1168.9 | J68: ні | K68: Клуб Рослин | L68: 1168.9 | M68: =IF(L68="","",E68-L68) | N68: =IF(OR(L68="",L68=0),"",M68/L68) | P68: 0 | Q68: 1 | R68: код | S68: відкрити
A69: Ваша ціна вища | B69: Ваша ціна вища на 2374.4 грн (155.7%); Немає в наявності в жодного постачальника | C69: 1001553 | D69: Гілкоріз площинний Фіскарс Fiskars PowerGear (M) L76 112300 (1001553) Фінляндія | E69: 3899 | F69: так | G69: 2299 | H69: ні | I69: 1524.6 | J69: ні | K69: Клуб Рослин | L69: 1524.6 | M69: =IF(L69="","",E69-L69) | N69: =IF(OR(L69="",L69=0),"",M69/L69) | P69: 0 | Q69: 1 | R69: код | S69: відкрити
A70: Ваша ціна вища | B70: Ваша ціна вища на 2840.4 грн (152.8%); Немає в наявності в жодного постачальника | C70: 1013564 | D70: Гілкоріз контактний Фіскарс Fiskars PowerStep SmartFit L86 112500 (1013564) Фінляндія | E70: 4699 | F70: так | G70: 2899 | H70: ні | I70: 1858.6 | J70: ні | K70: Клуб Рослин | L70: 1858.6 | M70: =IF(L70="","",E70-L70) | N70: =IF(OR(L70="",L70=0),"",M70/L70) | P70: 0 | Q70: 1 | R70: код | S70: відкрити
A71: Ваша ціна вища | B71: Ваша ціна вища на 1440.7 грн (150.3%); Немає в наявності в жодного постачальника | C71: 1001433 | D71: Кущоріз Фіскарс Fiskars SingleStep HS22 114730 (1001433) Фінляндія | E71: 2399 | F71: так | G71: 1699 | H71: ні | I71: 958.3 | J71: ні | K71: Клуб Рослин | L71: 958.3 | M71: =IF(L71="","",E71-L71) | N71: =IF(OR(L71="",L71=0),"",M71/L71) | P71: 0 | Q71: 1 | R71: код | S71: відкрити
A72: Ваша ціна вища | B72: Ваша ціна вища на 2830 грн (149.3%) | C72: P173-SL-85 | D72: Гілкоріз P173-SL-85 Bahco 850мм | E72: 4725 | F72: ні | I72: 1895 | J72: ні | K72: Клуб Рослин | L72: 1895 | M72: =IF(L72="","",E72-L72) | N72: =IF(OR(L72="",L72=0),"",M72/L72) | P72: 0 | Q72: 1 | R72: код | S72: відкрити
A73: Ваша ціна вища | B73: Ваша ціна вища на 417 грн (147.9%) | C73: 1000726 | D73: Садовий совок Фіскарс Fiskars Premium 137200 (1000726) Фінляндія | E73: 699 | F73: ні | G73: 549 | H73: ні | I73: 282 | J73: ні | K73: Клуб Рослин | L73: 282 | M73: =IF(L73="","",E73-L73) | N73: =IF(OR(L73="",L73=0),"",M73/L73) | P73: 0 | Q73: 1 | R73: код | S73: відкрити
A74: Ваша ціна вища | B74: Ваша ціна вища на 2977 грн (147.2%) | C74: 1001565 | D74: Ножиці для трави та живоплоту Фіскарс / Fiskars PowerLevel GS53 113710 (1001565) Фінляндія | E74: 4999 | F74: ні | G74: 3199 | H74: ні | I74: 2022 | J74: ні | K74: Клуб Рослин | L74: 2022 | M74: =IF(L74="","",E74-L74) | N74: =IF(OR(L74="",L74=0),"",M74/L74) | P74: 0 | Q74: 1 | R74: код | S74: відкрити
A75: Ваша ціна вища | B75: Ваша ціна вища на 945.6 грн (144.7%); Немає в наявності в жодного постачальника | C75: 1001533 | D75: Ножиці універсальні Фіскарс / Fiskars з петлею для пальців SP45 111450 (1001533) Фінляндія | E75: 1599 | F75: так | G75: 899 | H75: ні | I75: 653.4 | J75: ні | K75: Клуб Рослин | L75: 653.4 | M75: =IF(L75="","",E75-L75) | N75: =IF(OR(L75="",L75=0),"",M75/L75) | P75: 0 | Q75: 1 | R75: код | S75: відкрити
A76: Ваша ціна вища | B76: Ваша ціна вища на 2061.5 грн (143.4%); Немає в наявності в жодного постачальника | C76: 1000596 | D76: Ножиці для живоплоту з силовим приводом Фіскарс / Fiskars PowerGear HS72 114790 (1000596) Фінляндія | E76: 3499 | F76: так | I76: 1437.5 | J76: ні | K76: Клуб Рослин | L76: 1437.5 | M76: =IF(L76="","",E76-L76) | N76: =IF(OR(L76="",L76=0),"",M76/L76) | P76: 0 | Q76: 1 | R76: код | S76: відкрити
A77: Ваша ціна вища | B77: Ваша ціна вища на 679 грн (141.5%); Немає в наявності в жодного постачальника | C77: 1000680 | D77: Культиватор ручний 125 мм Fiskars QuikFit 136511 (1000680) Фінляндія | E77: 1159 | F77: так | G77: 799 | H77: ні | I77: 480 | J77: ні | K77: Клуб Рослин | L77: 480 | M77: =IF(L77="","",E77-L77) | N77: =IF(OR(L77="",L77=0),"",M77/L77) | P77: 0 | Q77: 1 | R77: код | S77: відкрити
A78: Ваша ціна вища | B78: Ваша ціна вища на 1397.1 грн (139.4%) | C78: 1001432 | D78: Гілкоріз площинний малий Фіскарс Fiskars із загнутими лезами SingleStep (S) L28 112160 (1001432) Фінляндія | E78: 2399 | F78: ні | G78: 1499 | H78: ні | I78: 1001.9 | J78: ні | K78: Клуб Рослин | L78: 1001.9 | M78: =IF(L78="","",E78-L78) | N78: =IF(OR(L78="",L78=0),"",M78/L78) | P78: 0 | Q78: 1 | R78: код | S78: відкрити
A79: Ваша ціна вища | B79: Ваша ціна вища на 2555 грн (138.6%) | C79: 1001615 | D79: Клин для розщеплення гвинтовий Фіскарс / Fiskars SAFE-T 120021 (1001615) Фінляндія | E79: 4399 | F79: ні | G79: 2799 | H79: ні | I79: 1844 | J79: ні | K79: Клуб Рослин | L79: 1844 | M79: =IF(L79="","",E79-L79) | N79: =IF(OR(L79="",L79=0),"",M79/L79) | P79: 0 | Q79: 1 | R79: код | S79: відкрити
A80: Ваша ціна вища | B80: Ваша ціна вища на 1848.6 грн (136.9%); Немає в наявності в жодного постачальника | C80: 1003609 | D80: Малий сікач для гілок Фіскарс Fiskars WoodXpert 126004 (1003609) Фінляндія | E80: 3199 | F80: так | G80: 2299 | H80: ні | I80: 1350.4 | J80: ні | K80: Клуб Рослин | L80: 1350.4 | M80: =IF(L80="","",E80-L80) | N80: =IF(OR(L80="",L80=0),"",M80/L80) | P80: 0 | Q80: 1 | R80: код | S80: відкрити
A81: Ваша ціна вища | B81: Ваша ціна вища на 1905.1 грн (136.7%) | C81: 1000590 | D81: Ножиці для трави подовжені з серво-системою Фіскарс / Fiskars GS46 113690 (1000590) Фінляндія | E81: 3299 | F81: ні | G81: 1999 | H81: ні | I81: 1393.9 | J81: ні | K81: Клуб Рослин | L81: 1393.9 | M81: =IF(L81="","",E81-L81) | N81: =IF(OR(L81="",L81=0),"",M81/L81) | P81: 0 | Q81: 1 | R81: код | S81: відкрити
A82: Ваша ціна вища | B82: Ваша ціна вища на 824.6 грн (132.1%) | C82: 1001614 | D82: Клин для розколу колод Фіскарс / Fiskars 120010 (1001614) Фінляндія | E82: 1449 | F82: ні | G82: 899 | H82: ні | I82: 624.4 | J82: ні | K82: Клуб Рослин | L82: 624.4 | M82: =IF(L82="","",E82-L82) | N82: =IF(OR(L82="",L82=0),"",M82/L82) | P82: 0 | Q82: 1 | R82: код | S82: відкрити
A83: Ваша ціна вища | B83: Ваша ціна вища на 142 грн (131.5%); Немає в наявності в жодного постачальника | C83: 1000696 | D83: Посадкова вилка Fiskars Solid 137030 (1000696) Фінляндія | E83: 250 | F83: так | G83: 249 | H83: ні | I83: 108 | J83: ні | K83: Клуб Рослин | L83: 108 | M83: =IF(L83="","",E83-L83) | N83: =IF(OR(L83="",L83=0),"",M83/L83) | P83: 0 | Q83: 1 | R83: код | S83: відкрити
A84: Ваша ціна вища | B84: Ваша ціна вища на 671 грн (127.1%); Немає в наявності в жодного постачальника | C84: 1000661 | D84: Штанга Фіскарс Fiskars QuikFit (L) 1560 мм 136001 (1000661) Фінляндія | E84: 1199 | F84: так | G84: 1049 | H84: ні | I84: 528 | J84: ні | K84: Клуб Рослин | L84: 528 | M84: =IF(L84="","",E84-L84) | N84: =IF(OR(L84="",L84=0),"",M84/L84) | P84: 0 | Q84: 1 | R84: код | S84: відкрити
A85: Ваша ціна вища | B85: Ваша ціна вища на 816.3 грн (123.6%); Немає в наявності в жодного постачальника | C85: 1000557 | D85: Ножиці для трави Фіскарс / Fiskars S50 111090 (1000557) Фінляндія | E85: 1477 | F85: так | I85: 660.7 | J85: ні | K85: Клуб Рослин | L85: 660.7 | M85: =IF(L85="","",E85-L85) | N85: =IF(OR(L85="",L85=0),"",M85/L85) | P85: 0 | Q85: 1 | R85: код | S85: відкрити
A86: Ваша ціна вища | B86: Ваша ціна вища на 1324.5 грн (123.3%) | C86: 1000600 | D86: Клин для розщеплення Фіскарс Fiskars 120020 (1000600) Фінляндія | E86: 2399 | F86: ні | G86: 1499 | H86: ні | I86: 1074.5 | J86: ні | K86: Клуб Рослин | L86: 1074.5 | M86: =IF(L86="","",E86-L86) | N86: =IF(OR(L86="",L86=0),"",M86/L86) | P86: 0 | Q86: 1 | R86: код | S86: відкрити
A87: Ваша ціна вища | B87: Ваша ціна вища на 1100 грн (122.4%) | C87: 1001562 | D87: Плодознімач-насадка Фіскарс / Fiskars (1001562) Фінляндія | E87: 1999 | F87: ні | G87: 899 | H87: ні | K87: Водоспад | L87: 899 | M87: =IF(L87="","",E87-L87) | N87: =IF(OR(L87="",L87=0),"",M87/L87) | P87: 0 | Q87: 1 | R87: код | S87: відкрити
A88: Ваша ціна вища | B88: Ваша ціна вища на 481 грн (121.5%); Немає в наявності в жодного постачальника | C88: 1000601 | D88: Точилка для сокир і ножів Фіскарс Fiskars Xsharp 120740 (1000601) Фінляндія | E88: 877 | F88: так | G88: 599 | H88: ні | I88: 396 | J88: ні | K88: Клуб Рослин | L88: 396 | M88: =IF(L88="","",E88-L88) | N88: =IF(OR(L88="",L88=0),"",M88/L88) | P88: 0 | Q88: 1 | R88: код | S88: відкрити
A89: Ваша ціна вища | B89: Ваша ціна вища на 1078.8 грн (119.8%); Немає в наявності в жодного постачальника | C89: 1000656 | D89: Граблі Фіскарс Fiskars QuikFit 135514 (1000656) Фінляндія | E89: 1979 | F89: так | G89: 1599 | H89: ні | I89: 900.2 | J89: ні | K89: Клуб Рослин | L89: 900.2 | M89: =IF(L89="","",E89-L89) | N89: =IF(OR(L89="",L89=0),"",M89/L89) | P89: 0 | Q89: 1 | R89: код | S89: відкрити
A90: Ваша ціна вища | B90: Ваша ціна вища на 2395.2 грн (119.5%) | C90: 1000583 | D90: Гілкоріз великий контактний Фіскарс / Fiskars PowerGear (L) L77 112580 (1000583) Фінляндія | E90: 4399 | F90: ні | G90: 2699 | H90: ні | I90: 2003.8 | J90: ні | K90: Клуб Рослин | L90: 2003.8 | M90: =IF(L90="","",E90-L90) | N90: =IF(OR(L90="",L90=0),"",M90/L90) | P90: 0 | Q90: 1 | R90: код | S90: відкрити
A91: Ваша ціна вища | B91: Ваша ціна вища на 1197.1 грн (119.5%) | C91: 1000581 | D91: Гілкоріз малий контактний Фіскарс Fiskars PowerGear (S) L31 112170 (1000581) Фінляндія | E91: 2199 | F91: ні | G91: 1299 | H91: ні | I91: 1001.9 | J91: ні | K91: Клуб Рослин | L91: 1001.9 | M91: =IF(L91="","",E91-L91) | N91: =IF(OR(L91="",L91=0),"",M91/L91) | P91: 0 | Q91: 1 | R91: код | S91: відкрити
A92: Ваша ціна вища | B92: Ваша ціна вища на 1126.2 грн (115.8%) | C92: 1000589 | D92: Ножиці для трави з Серво-системою Фіскарс Fiskars GS42 113680 (1000589) Фінляндія | E92: 2099 | F92: ні | G92: 1399 | H92: ні | I92: 972.8 | J92: ні | K92: Клуб Рослин | L92: 972.8 | M92: =IF(L92="","",E92-L92) | N92: =IF(OR(L92="",L92=0),"",M92/L92) | P92: 0 | Q92: 1 | R92: код | S92: відкрити
A93: Ваша ціна вища | B93: Ваша ціна вища на 1548.6 грн (114.7%) | C93: 1001564 | D93: Ножиці для живоплоту Фіскарс / Fiskars PowerLever HS52 114750 (1001564) Фінляндія | E93: 2899 | F93: ні | G93: 1799 | H93: ні | I93: 1350.4 | J93: ні | K93: Клуб Рослин | L93: 1350.4 | M93: =IF(L93="","",E93-L93) | N93: =IF(OR(L93="",L93=0),"",M93/L93) | P93: 0 | Q93: 1 | R93: код | S93: відкрити
A94: Ваша ціна вища | B94: Ваша ціна вища на 2295.2 грн (114.5%) | C94: 1013565 | D94: Ножиці для живоплоту телескопічні Фіскарс / Fiskars SmartFit HS86 114800 (1013565) Фінляндія | E94: 4299 | F94: ні | G94: 2799 | H94: ні | I94: 2003.8 | J94: ні | K94: Клуб Рослин | L94: 2003.8 | M94: =IF(L94="","",E94-L94) | N94: =IF(OR(L94="",L94=0),"",M94/L94) | P94: 0 | Q94: 1 | R94: код | S94: відкрити
A95: Ваша ціна вища | B95: Ваша ціна вища на 2229.8 грн (113.8%); Немає в наявності в жодного постачальника | C95: 1000640 | D95: Бур садовий Фіскарс Fiskars QuikDrill L великий 134730 (1000640) Фінляндія | E95: 4190 | F95: так | G95: 2699 | H95: ні | I95: 1960.2 | J95: ні | K95: Клуб Рослин | L95: 1960.2 | M95: =IF(L95="","",E95-L95) | N95: =IF(OR(L95="",L95=0),"",M95/L95) | P95: 0 | Q95: 1 | R95: код | S95: відкрити
A96: Ваша ціна вища | B96: Ваша ціна вища на 659.21 грн (108.1%); Немає в наявності в жодного постачальника | C96: 1000654 | D96: Граблі для грунту 16 зубів Fiskars QuikFit 135512 (1000654) Фінляндія | E96: 1269 | F96: так | G96: 899 | H96: ні | I96: 609.79 | J96: ні | K96: Клуб Рослин | L96: 609.79 | M96: =IF(L96="","",E96-L96) | N96: =IF(OR(L96="",L96=0),"",M96/L96) | P96: 0 | Q96: 1 | R96: код | S96: відкрити
A97: Ваша ціна вища | B97: Ваша ціна вища на 1181 грн (105.6%); Немає в наявності в жодного постачальника | C97: 1001426 | D97: Гілкоріз площинний великий Фіскарс Fiskars SingleStep L38 112460 (1001426) Фінляндія | E97: 2299 | F97: так | G97: 1449 | H97: ні | I97: 1118 | J97: ні | K97: Клуб Рослин | L97: 1118 | M97: =IF(L97="","",E97-L97) | N97: =IF(OR(L97="",L97=0),"",M97/L97) | P97: 0 | Q97: 1 | R97: код | S97: відкрити
A98: Ваша ціна вища | B98: Ваша ціна вища на 1940.4 грн (104.4%) | C98: 1000638 | D98: Бур садовий Фіскарс Fiskars QuikDrill M середній 134720 (1000638) Фінляндія | E98: 3799 | F98: ні | G98: 2499 | H98: ні | I98: 1858.6 | J98: ні | K98: Клуб Рослин | L98: 1858.6 | M98: =IF(L98="","",E98-L98) | N98: =IF(OR(L98="",L98=0),"",M98/L98) | P98: 0 | Q98: 1 | R98: код | S98: відкрити
A99: Ваша ціна вища | B99: Ваша ціна вища на 357 грн (104.4%) | C99: 1000727 | D99: Совок для розсади Фіскарс / Fiskars Premium 137210 (1000727) Фінляндія | E99: 699 | F99: ні | G99: 549 | H99: ні | I99: 342 | J99: ні | K99: Клуб Рослин | L99: 342 | M99: =IF(L99="","",E99-L99) | N99: =IF(OR(L99="",L99=0),"",M99/L99) | P99: 0 | Q99: 1 | R99: код | S99: відкрити
A100: Ваша ціна вища | B100: Ваша ціна вища на 1131 грн (101.2%) | C100: 1001556 | D100: Гілкоріз малий контактний Фіскарс Fiskars PowerGear (S) L71 112180 (1001556) Фінляндія | E100: 2249 | F100: ні | I100: 1118 | J100: ні | K100: Клуб Рослин | L100: 1118 | M100: =IF(L100="","",E100-L100) | N100: =IF(OR(L100="",L100=0),"",M100/L100) | P100: 0 | Q100: 1 | R100: код | S100: відкрити
...

Sheet Журнал змін
A1: Дата | B1: Хто змінив | C1: Мій ID | D1: ID у постачальника | E1: Товар | F1: Було, грн | G1: Стало, грн | H1: Зміна, грн | I1: Зміна, %

Sheet Ціни постачальників по днях
A1: Постачальник | B1: Мій ID | C1: ID у постачальника | D1: Товар | E1: 08.10
A2: Водоспад | B2: 123100400 | C2: 42494 | D2: Точильний камінь 4000/1000 S&R (123100400) Німеччина | E2: 5690
A3: Водоспад | B3: 123100402 | C3: 42494 | D3: Набір точильних каменів 120/240 та 4000/1000 гріт S&R (123100402) Німеччина | E3: 5690
A4: Клуб Рослин | B4: SD-95-PN | C4: 15592 | D4: Точилка діамантова для вигнутих країв АРС / ARS Pen (SD-95-PN) Японія | E4: 1599
A5: Водоспад | B5: 0.600.8B2.100 | C5: 41370 | D5: Секатор Bosch EasyPrune акумуляторний (0.600.8B2.100) Німеччина | E5: 5802
A6: Клуб Рослин | B6: 7249 | C6: 15530 | D6: Добриво Преміум Фоліар Premium Foliar 19-19-19+ТЕ 15 кг AgroWork Туреччина | E6: 2799
A7: Клуб Рослин | B7: 120500200101 | C7: 10596 | D7: Маркер перманентний Baumschulen чорний 2 мм (120500200101) Німеччина | E7: 178
A8: Водоспад | B8: P57-25-F | C8: 42609 | D8: Кущоріз Bahco P57-25-F Бахо | E8: 2590
A9: Водоспад | B9: PX-M3-R500P | C9: 37459 | D9: Секатор Bahco PX-M3 для обрізки саду | E9: 2050
A10: Клуб Рослин | B10: PX-M3-R500P | C10: 11858 | D10: Секатор Bahco PX-M3 для обрізки саду | E10: 2950
A11: Водоспад | B11: 11827 | C11: 41088 | D11: Ніж Morakniv Companion MG Olive (11827) Mora Швеція | E11: 799
A12: Водоспад | B12: Rain1 | C12: 40534 | D12: Опадомір (дощомір) пластиковий 0-50 mm L/m2 (Rain1) Corteva | E12: 220
A13: Водоспад | B13: BCL20IB | C13: 39101 | D13: Секатор акумуляторний Bahco BCL20IB Бахо | E13: 16999
... A675: Водоспад | B675: 3.90.20 | C675: 32375 | D675: ​​​​​​​Ніж для щеплення Victorinox 3.90.20 Швейцарія | E675: 1449

Sheet Ваші ціни по днях
A1: Постачальник | B1: Мій ID | C1: ID у постачальника | D1: Товар | E1: 08.10
A2: Водоспад | B2: 123100400 | C2: 42494 | D2: Точильний камінь 4000/1000 S&R (123100400) Німеччина | E2: 540
A3: Водоспад | B3: 123100402 | C3: 42494 | D3: Набір точильних каменів 120/240 та 4000/1000 гріт S&R (123100402) Німеччина | E3: 755
A4: Клуб Рослин | B4: SD-95-PN | C4: 15592 | D4: Точилка діамантова для вигнутих країв АРС / ARS Pen (SD-95-PN) Японія | E4: 849
A5: Водоспад | B5: 0.600.8B2.100 | C5: 41370 | D5: Секатор Bosch EasyPrune акумуляторний (0.600.8B2.100) Німеччина | E5: 4245
A6: Клуб Рослин | B6: 7249 | C6: 15530 | D6: Добриво Преміум Фоліар Premium Foliar 19-19-19+ТЕ 15 кг AgroWork Туреччина | E6: 2250
A7: Клуб Рослин | B7: 120500200101 | C7: 10596 | D7: Маркер перманентний Baumschulen чорний 2 мм (120500200101) Німеччина | E7: 145
A8: Водоспад | B8: P57-25-F | C8: 42609 | D8: Кущоріз Bahco P57-25-F Бахо | E8: 2160
A9: Водоспад | B9: PX-M3-R500P | C9: 37459 | D9: Секатор Bahco PX-M3 для обрізки саду | E9: 2500
A10: Клуб Рослин | B10: PX-M3-R500P | C10: 11858 | D10: Секатор Bahco PX-M3 для обрізки саду | E10: 2500
A11: Водоспад | B11: 11827 | C11: 41088 | D11: Ніж Morakniv Companion MG Olive (11827) Mora Швеція | E11: 699
A12: Водоспад | B12: Rain1 | C12: 40534 | D12: Опадомір (дощомір) пластиковий 0-50 mm L/m2 (Rain1) Corteva | E12: 198
A13: Водоспад | B13: BCL20IB | C13: 39101 | D13: Секатор акумуляторний Bahco BCL20IB Бахо | E13: 15525
... A675: Водоспад | B675: 3.90.20 | C675: 32375 | D675: ​​​​​​​Ніж для щеплення Victorinox 3.90.20 Швейцарія | E675: 1449

Sheet Пари на перевірку
A1: Скрипт не наважився зіставити ці товари сам. Щоб підтвердити пару, відкрийте mapping/suggestions.csv на GitHub і впишіть «так» у колонку «рішення», щоб відхилити, «ні».
A2: Схожість | B2: Постачальник | C2: Мій ID | D2: ID у постачальника | E2: Мій товар | F2: Товар постачальника | G2: Моя ціна, грн | H2: Ціна постачальника, грн | I2: Причина
A3: 97.2 | B3: Водоспад | C3: 8.107 | D3: 32356 | E3: Садовий секатор із наковаленкою LOWE Original 8.107 | F3: Садовий секатор із наковаленкою LOWE Original 8.107 (8.107) | G3: 2990 | H3: 2990 | I3: назви схожі, перевірте
A4: 97.1 | B4: Водоспад | C4: BCL25IB | D4: 39101 | E4: Секатор акумуляторний Bahco BCL25IB | F4: Акумуляторний секатор Bahco (BCL20IB) | G4: 33750 | H4: 16999 | I4: назви схожі, перевірте
A5: 95.7 | B5: Водоспад | C5: BCL240 | D5: 39101 | E5: Секатор акумуляторний Bahco BCL240 | F5: Акумуляторний секатор Bahco (BCL20IB) | G5: 20025 | H5: 16999 | I5: назви схожі, але різні коди виробника
A6: 95.6 | B6: Водоспад | C6: PROF-H | D6: 42566 | E6: Шкіряний чохол Bahco PROF-H Бахо | F6: Чохол шкіряний BAHCO (PROF-H) | G6: 1350 | H6: 1390 | I6: назви схожі, різняться словами: бахо
A7: 95 | B7: Клуб Рослин | C7: 5770/R | D7: 10823 | E7: Ніж для щеплення універсальний високовуглецева сталь хобі Антоніні / Antonini (5770/R) Італія | F7: Ніж Antonini 5770/R для щеплення універсальний високовуглецева сталь хобі | G7: 450 | H7: 450 | I7: назви схожі, різняться словами: антоніні
A8: 94.7 | B8: Клуб Рослин | C8: 702 | D8: 15822 | E8: Секатор садовий обвідний Йошіока Хамоно / Yoshioka Hamono (702) | F8: Секатор Yoshioka Hamono 702 японський садовий обвідний (Йошіока Хамоно 702) | G8: 1990 | H8: 1990 | I8: назви схожі, різняться словами: японський
A9: 94.7 | B9: Клуб Рослин | C9: 701-1 | D9: 15821 | E9: Секатор садовий обвідний Йошіока Хамоно / Yoshioka Hamono (701) | F9: Секатор Yoshioka Hamono 701 японський садовий обвідний (Йошіока Хамоно 701) | G9: 1890 | H9: 1890 | I9: назви схожі, різняться словами: японський
A10: 94.7 | B10: Клуб Рослин | C10: 5016/L | D10: 10810 | E10: Ніж для щеплення універсальний високовуглецева сталь Антоніні / Antonini (5016/L) Італія | F10: Ніж Antonini 5016/L для щеплення універсальний високовуглецева сталь | G10: 1260 | H10: 1130 | I10: назви схожі, різняться словами: антоніні
A11: 94.7 | B11: Клуб Рослин | C11: 5016/N | D11: 10812 | E11: Ніж для щеплення універсальний високовуглецева сталь Антоніні / Antonini (5016/N) Італія | F11: Ніж Antonini 5016/N для щеплення універсальний високовуглецева сталь | G11: 1130 | H11: 1130 | I11: назви схожі, різняться словами: антоніні
A12: 94.7 | B12: Клуб Рослин | C12: 5016/R | D12: 10813 | E12: Ніж для щеплення універсальний високовуглецева сталь Антоніні / Antonini (5016/R) Італія | F12: Ніж Antonini 5016/R для щеплення універсальний високовуглецева сталь | G12: 1130 | H12: 1130 | I12: назви схожі, різняться словами: антоніні
A13: 94.6 | B13: Водоспад | C13: 9.107 | D13: 32327 | E13: LOWE Original 9.107 обхідний секатор Німеччина | F13: Обхідний секатор LOWE 9.107 (Німеччина) | G13: 3190 | H13: 3190 | I13: назви схожі, різняться словами: original
A14: 94.6 | B14: Водоспад | C14: 9.104 | D14: 32326 | E14: LOWE Original 9.104 Обхідний секатор Німеччина | F14: Обхідний секатор LOWE 9.104 (Німеччина) | G14: 3190 | H14: 3190 | I14: назви схожі, різняться словами: original
... A45: 90.5 | B45: Клуб Рослин | C45: 640 | D45: 11216 | E45: Пила в кобурі 440 мм Фелко / Felco 640 Швейцарія | F45: Пила в кобурі Felco 640 (Фелко 640) | G45: 3490 | H45: 3490 | I45: назви схожі, перевірте
A46: 90.5 | B46: Клуб Рослин | C46: ddd10be1-abba-11ee-bf43-c87f546feb15 | D46: 9622 | E46: Окуляри захисні | F46: Захисні окуляри LESO-TR | H46: 70 | I46: назви схожі, різняться словами: lesotr
A47: 90.4 | B47: Водоспад | C47: 605/11 | D47: 32936 | E47: Щеплювальний ніж універсальний Тіна / Tina (605/11) Німеччина | F47: Ніж універсальний TINA 605/11 (Німеччина) | G47: 4999 | H47: 4999 | I47: назви схожі, різняться словами: тіна, щеплювальний
A48: 90.4 | B48: Клуб Рослин | C48: 3604-21.B | D48: 11876 | E48: Секатор 210 мм універсальний Bellota (3604-21.B) Іспанія | F48: Секатор Bellota 3604-21 універсальний | G48: 1989 | H48: 1989 | I48: назви схожі, але різні коди виробника
A49: 90.3 | B49: Клуб Рослин | C49: SR-BAG.L | D49: 16238 | E49: Сумка Смарт Рейн / Smart Rain 400 л (SR-BAG.L) | F49: Сумка Smart Rain 280 л SR-BAG (Смарт Рейн SR-BAG) | G49: 995 | H49: 695 | I49: назви схожі, але різні об'єми або розміри
A50: 90.3 | B50: Клуб Рослин | C50: 646283f3-abbb-11ee-bf43-c87f546feb15 | D50: 11884 | E50: Секатор Due Buoi 175 см (1145/17.5) типу ножиці довгі леза Дю Буі | F50: Секатор Due Buoi 1145/17,5 типу ножиці довгі леза (Дуе Буаї) | G50: 419 | H50: 496 | I50: код збігся, але різні коди виробника
A51: 90.2 | B51: Клуб Рослин | C51: P6202 | D51: 16018 | E51: Серп-коса для трави 37 см Фукс / Fux (P6202) Австрія | F51: Серп-Коса 35 см FUX 2 для трави (Фукс P6202) | G51: 2650 | H51: 2650 | I51: назви схожі, але різні об'єми або розміри
A52: 90 | B52: Водоспад | C52: 606 | D52: 32935 | E52: Щеплювальний ніж універсальний Тіна / Tina (606) Німеччина | F52: Ніж універсальний TINA 606 (Німеччина) | G52: 4799 | H52: 4799 | I52: назви схожі, різняться словами: тіна, щеплювальний
A53: 90 | B53: Водоспад | C53: 605 | D53: 32806 | E53: Щеплювальний ніж універсальний Тіна / Tina (605) Німеччина | F53: Ніж універсальний TINA 605 (Німеччина) | G53: 4799 | H53: 4799 | I53: назви схожі, різняться словами: тіна, щеплювальний
A54: 90 | B54: Клуб Рослин | C54: 3512-21.B | D54: 11872 | E54: Секатор 210 мм професійний Bellota (3512-21.B) Іспанія | F54: Секатор Bellota 3512-21 професійний | G54: 2798 | H54: 2798 | I54: назви схожі, але різні коди виробника
A55: 90 | B55: Клуб Рослин | C55: 3510-21.B | D55: 11871 | E55: Секатор 210 мм професійний Bellota (3510-21.B) Іспанія | F55: Секатор Bellota 3510-21 професійний | G55: 2649 | H55: 2649 | I55: назви схожі, але різні коди виробника
A56: 90 | B56: Клуб Рослин | C56: CAM-24LN | D56: 11177 | E56: Пила АРС / ARS (CAM-24LN) з кобурою Японія | F56: Пила з кобурою ARS CAM-24LN (АРС CAM-24LN) | G56: 1459 | H56: 1459 | I56: назви схожі, але різні коди виробника
A57: 89.9 | B57: Клуб Рослин | C57: VS-9XZ | D57: 11843 | E57: Секатор АРС / ARS (VS-9XZ) професійний обвідний Японія | F57: Секатор ARS VS-9Z професійний обвідний (АРС VS-9Z) | G57: 2519 | H57: 1490 | I57: назви схожі, але різні коди виробника
A58: 89.8 | B58: Клуб Рослин | C58: 7104 | D58: 9312 | E58: Добриво Монокалій фосфат 0-52-34 Nova Peak 25 кг ICL Ізраїль | F58: Добриво водорозчинне Монокалій фосфат ICL Novapeak 0-52-34 (Ізраїль), 25 кг | G58: 3798 | H58: 3950 | I58: назви схожі, різняться словами: водорозчинне
... A79: 88.5 | B79: Клуб Рослин | C79: 3461-C.B. | D79: 11019 | E79: Ножиці для обрізки кущів Bellota (3461-C.B.) Іспанія | F79: Ножиці для кущів Bellota 3461-C | G79: 1845 | H79: 2287 | I79: назви схожі, різняться словами: обрізки
A80: 88.2 | B80: Водоспад | C80: ddd10b7f-abba-11ee-bf43-c87f546feb15 | D80: 38700 | E80: Садові ножиці | F80: Садові ножиці ARS (310) | H80: 445 | I80: назви схожі, різняться словами: ars
A81: 88.1 | B81: Клуб Рослин | C81: 3510-21D.B | D81: 12061 | E81: Секатор 210 мм професійний для великих рук Bellota (3510-21D.B) Іспанія | F81: Секатор професійний Bellota 3512-22.B для великих рук | G81: 2369 | H81: 1909 | I81: назви схожі, але різні коди виробника
A82: 88.1 | B82: Клуб Рослин | C82: 3556.B | D82: 11047 | E82: Ножиці довгомірні для підрізування трави Bellota (3556.B) Іспанія | F82: Ножиці довгомірні Bellota 3556.B для підрізки трави | G82: 2314 | H82: 2314 | I82: назви схожі, різняться словами: підрізки, підрізування
A83: 88.1 | B83: Клуб Рослин | C83: HT-R11 | D83: 10978 | E83: Ніж для степлера HT-R1 MAX Tapener (комплект 2шт) | F83: Ніж для степлера HR-F Max (комплект 5шт) | G83: 250 | H83: 230 | I83: назви схожі, але різні об'єми або розміри
A84: 88 | B84: Водоспад | C84: 3083.B | D84: 43391 | E84: Сапка рамкова без держака 150 мм Bellota (3083.B) Іспанія | F84: Сапка рамкова Bellota 3083.B (плоскоріз) 150 мм без держака | G84: 485 | H84: 469 | I84: назви схожі, різняться словами: плоскоріз
A85: 88 | B85: Клуб Рослин | C85: 611 | D85: 11213 | E85: Пила в кобурі 500 мм Felco / Фелко 611 Швейцарія | F85: Пила в кобурі Felco 611 (Фелко 611) | G85: 2990 | H85: 2990 | I85: назви схожі, перевірте
A86: 87.8 | B86: Водоспад | C86: N9.107 | D86: 43329 | E86: Секатор обвідний Lowe Natural Series (N9.107) дерев’яні ручки Німеччина | F86: Секатор обвідний LOWE N9.107 Natural Series, зріз 22 мм, дерев’яні ручки з гікорі | G86: 5499 | H86: 5499 | I86: назви схожі, різняться словами: гікорі, зріз
A87: 87.8 | B87: Водоспад | C87: N9.104 | D87: 43323 | E87: Секатор обвідний Lowe Natural Series (N9.104) дерев’яні ручки Німеччина | F87: Секатор обвідний LOWE N9.104 Natural Series, зріз 22 мм, дерев’яні ручки з гікорі | G87: 5499 | H87: 5499 | I87: назви схожі, різняться словами: гікорі, зріз
A88: 87.8 | B88: Водоспад | C88: 3580-CH.B | D88: 37700 | E88: Запасне контрлезо для гілкоріза 3580 (3580-CH.B) Bellota Іспанія | F88: Запасне контрлезо 3580 Bellota (3580-CH) | G88: 1259 | H88: 1210 | I88: назви схожі, але різні коди виробника
A89: 87.7 | B89: Клуб Рослин | C89: 3344 | D89: 12851 | E89: Фунгіцид Парацельс 100 мл Сімейний Сад Україна | F89: Фунгіцид Парацельс К.С. (флутриафол) 100 мл Сімейний Сад | G89: 198 | H89: 178 | I89: назви схожі, різняться словами: флутриафол
A90: 87.6 | B90: Клуб Рослин | C90: 3505-23.B | D90: 12061 | E90: Секатор 228 мм професійний для великих рук Bellota (3505-23.B) Іспанія | F90: Секатор професійний Bellota 3512-22.B для великих рук | G90: 2054 | H90: 1909 | I90: назви схожі, але різні коди виробника
A91: 87.6 | B91: Клуб Рослин | C91: 7238 | D91: 9236 | E91: Добриво Терафлекс Пасльоновий Terraflex Т (15-8-25 + 3.5 MgO + TЕ) 2 кг SmartGrow Бельгія | F91: Добриво Terraflex T 15-8-25+3,5MgO+TE (Терафлекс), 2 кг | G91: 475 | H91: 377 | I91: назви схожі, різняться словами: smartgrow, пасльоновий
A92: 87.5 | B92: Водоспад | C92: 9809 | D92: 41796 | E92: Чохол шкіряний Lowe (9809) Льове Німеччина | F92: Чохол шкіряний LOWE (9809) | G92: 2090 | H92: 2090 | I92: назви схожі, різняться словами: льове
... A97: 87.2 | B97: Водоспад | C97: 135/20 | D97: 33212 | E97: Секатор Due Buoi 135/20 Італія | F97: Секатор для обрізання дерев Due Buoi 135/20 (Італія) | G97: 2550 | H97: 2550 | I97: назви схожі, різняться словами: дерев, обрізання
A98: 87.2 | B98: Клуб Рослин | C98: ddd10bb3-abba-11ee-bf43-c87f546feb15 | D98: 11039 | E98: Ножиці для трави | F98: Ножиці для трави Bahco GS-76 | H98: 990 | I98: назви схожі, різняться словами: bahco
A99: 87.1 | B99: Клуб Рослин | C99: С 013 | D99: 16108 | E99: Держак металевий для садового інструменту Смарт Рейн / Smart Rain (С 013) Україна | F99: Держак Smart Rain металевий трисекційний для садового інструменту 215 см С 014 (Смарт Рейн С 014) | G99: 745 | H99: 745 | I99: назви схожі, різняться словами: трисекційний
A100: 87 | B100: Клуб Рослин | C100: MF20ММ | D100: 10972 | E100: Ніж-кільце для обрізки кембрика металевий IMF 20 мм Італія | F100: Ніж для обрізки кембрика металевий | G100: 290 | H100: 150 | I100: назви схожі, різняться словами: imf, кільце
A101: 86.9 | B101: Клуб Рослин | C101: 1-500 | D101: 14962 | E101: Садова замазка Balsam Pro / Бальзам Про 500 г Royal Mix | F101: Садова замазка Balsam Pro Royal Mix 500 г (Роял Мікс) | G101: 539 | H101: 550 | I101: назви схожі, різняться словами: бальзам, мікс, роял
A102: 86.9 | B102: Клуб Рослин | C102: 1-250 | D102: 14961 | E102: Садова замазка Balsam Pro / Бальзам Про 250 г Royal Mix | F102: Садова замазка Balsam Pro Royal Mix 250 г (Роял Мікс) | G102: 250 | H102: 345 | I102: назви схожі, різняться словами: бальзам, мікс, роял
A103: 86.8 | B103: Водоспад | C103: 202AP | D103: 33187 | E103: Ніж Due Buoi 202AP для щеплення універсальний Італія | F103: Ніж для щеплення Due Buoi 224P (Італія) | G103: 1990 | H103: 890 | I103: назви схожі, різняться словами: універсальний
A104: 86.8 | B104: Водоспад | C104: 12ANTAPL | D104: 40555 | E104: Ніж-кільце пластиковий на палець 20 / 24мм (12ANTAPL) Італія | F104: Ніж-кільце на палець пластиковий 20/24мм cod.502 (12ANTAPL) | G104: 195 | H104: 195 | I104: код збігся, але різні об'єми або розміри
A105: 86.8 | B105: Клуб Рослин | C105: 3076.B | D105: 14024 | E105: Набір садових інструментів з алюмінію 3 предмети Bellota (3076.B) Іспанія | F105: Набір садових інструментів (3 од.) Bellota, 3076.B | G105: 1579 | H105: 1579 | I105: назви схожі, різняться словами: алюмінію, предмети
A106: 86.8 | B106: Клуб Рослин | C106: 2C_387/20 | D106: 11904 | E106: Секатор з храповим механізмом Due Cigni 200 мм (2C_387/20) Італія | F106: Секатор Due Cigni 387/20 з храповим механізмом (Дуе Чіні) | G106: 900 | H106: 900 | I106: назви схожі, різняться словами: чіні
A107: 86.7 | B107: Клуб Рослин | C107: 2260 | D107: 14076 | E107: Інсектицид Синерид 100 мл Сімейний Сад Україна | F107: Інсектицид Синерид М.Д. (тіаклоприд) 100 мл Сімейний Сад | G107: 248 | H107: 309 | I107: назви схожі, різняться словами: тіаклоприд
A108: 86.6 | B108: Водоспад | C108: FAL00902 | D108: 41178 | E108: Камінь точильний штучний 200х20х10 мм 240 Grit Falket / Фалкет (FAL00902) Італія | F108: Камінь точильний штучний, 200х20х10 мм, 240 GRIT, FALKET (00902) | G108: 480 | H108: 480 | I108: назви схожі, але різні коди виробника
A109: 86.6 | B109: Клуб Рослин | C109: 150 | D109: 14600 | E109: Садовий секатор обвідний Альпен / Alpen Gelbhorn 207 мм (150) Швейцарія | F109: Садовий секатор Alpen Gelbhorn 150 обвідний (Альпен Гелбхорн 150) | G109: 1299 | H109: 1299 | I109: назви схожі, різняться словами: гелбхорн
A110: 86.6 | B110: Клуб Рослин | C110: 140 | D110: 14599 | E110: Садовий секатор обвідний Альпен / Alpen Gelbhorn 193 мм (140) Швейцарія | F110: Садовий секатор Alpen Gelbhorn 140 обвідний (Альпен Гелбхорн 140) | G110: 780 | H110: 780 | I110: назви схожі, різняться словами: гелбхорн
... A161: 84.9 | B161: Клуб Рослин | C161: 8091 | D161: 13641 | E161: Добриво Osmocote / Хобі Осмокот для квітучих рослин 12-7-18 (2-3 М) ICL 1 кг Ізраїль | F161: Добриво тривалої дії Хобі Осмокот для квітучих рослин 12-7-18+Te (2-3 місяця), 1 кг - Osmocote | G161: 459 | H161: 280 | I161: назви схожі, різняться словами: icl, місяця, тривалої
A162: 84.8 | B162: Водоспад | C162: ddd10bb3-abba-11ee-bf43-c87f546feb15 | D162: 39929 | E162: Ножиці для трави | F162: Ножиці для трави Bellota (3555/B) | H162: 1029 | I162: назви схожі, різняться словами: bellota
A163: 84.8 | B163: Клуб Рослин | C163: 260 | D163: 14602 | E163: Гілкоріз обвідний Альпен Вейссхорн / Alpen Weisshorn (260) Швейцарія | F163: Сучкоріз Alpen Weisshorn 260 обвідний (Альпен Вейссхорн 260) | G163: 2075 | H163: 2075 | I163: назви схожі, різняться словами: гілкоріз, сучкоріз
A164: 84.7 | B164: Клуб Рослин | C164: 630/11 | D164: 10941 | E164: Ніж садовий для обрізки Тіна / Tina (630/11) Німеччина | F164: Ніж Tina 630/11 для обрізки | G164: 6999 | H164: 6999 | I164: назви схожі, різняться словами: садовий, тіна
A165: 84.7 | B165: Клуб Рослин | C165: 626/11 | D165: 10940 | E165: Ніж садовий для обрізки Тіна / Tina (626/11) Німеччина | F165: Ніж Tina 626/11 для обрізки | G165: 6599 | H165: 6599 | I165: назви схожі, різняться словами: садовий, тіна
A166: 84.7 | B166: Клуб Рослин | C166: K-900Z | D166: 11015 | E166: Ножиці для кущів АРС / ARS (К-900Z) Японія | F166: Ножиці для кущів ARS K-800 (АРС K-800) | G166: 3690 | H166: 2389 | I166: назви схожі, але різні коди виробника
A167: 84.7 | B167: Клуб Рослин | C167: 3612.B | D167: 11877 | E167: Секатор довгомірний телескопічний 1500 мм Bellota (3612.B) Іспанія | F167: Секатор Bellota 3612 телескопічний | G167: 3429 | H167: 3429 | I167: назви схожі, різняться словами: довгомірний
A168: 84.7 | B168: Клуб Рослин | C168: 613/20 | D168: 11022 | E168: Ножиці для кущів Due Buoi 613/20 Італія | F168: Ножиці для кущів Due Buoi 613/20 (Дюе Буаі) | G168: 1990 | H168: 1990 | I168: назви схожі, різняться словами: буаі
A169: 84.7 | B169: Клуб Рослин | C169: 2021 | D169: 14086 | E169: Інсектицид Турбо Престо 500 мл Сімейний Сад | F169: Інсектицид Турбо Престо М.Д. (клотіанідін + лямбда-цигалотрин + ПЕГ) 500 мл Сімейний Сад | G169: 775 | H169: 856 | I169: назви схожі, різняться словами: клотіанідін, лямбда, цигалотрин
A170: 84.6 | B170: Водоспад | C170: 247P | D170: 33174 | E170: Щеплювальний ніж Due Buoi 247P Італія | F170: Окулювальний ніж Due Buoi 214P-SP-OT (Італія) | G170: 1990 | H170: 870 | I170: назви схожі, різняться словами: окулювальний, щеплювальний
A171: 84.6 | B171: Клуб Рослин | C171: 980 | D171: 12362 | E171: Спрей для очищення і захисту​​​​​​​ Фелко / Felco 980 Швейцарія | F171: Спрей для очищування і захисту Felco 980 (Фелко 980) | G171: 669 | H171: 669 | I171: назви схожі, різняться словами: очищення, очищування
A172: 84.6 | B172: Клуб Рослин | C172: 1-200 | D172: 14962 | E172: Садова замазка Balsam Pro / Бальзам Про 200 г Royal Mix | F172: Садова замазка Balsam Pro Royal Mix 500 г (Роял Мікс) | G172: 329 | H172: 550 | I172: назви схожі, але різні об'єми або розміри
A173: 84.5 | B173: Водоспад | C173: 1.107 | D173: 32335 | E173: Секатор з ковадлом Льове / Lowe Original (1.107) Німеччина | F173: Секатор з ковадлом LOWE Original 2.107 (2.107) | G173: 2220 | H173: 2440 | I173: назви схожі, різняться словами: льове
A174: 84.4 | B174: Клуб Рослин | C174: 2182 | D174: 14082 | E174: Інсектицид Турбо Престо 3 Active (Актив) 500 мл Сімейний Сад | F174: Інсектицид Турбо Престо 3 Active К.С. (клотіанідін + лямбда-цигалотрин + ППБ) 500 мл Сімейний Сад | G174: 1142 | H174: 1569 | I174: назви схожі, різняться словами: актив, клотіанідін, лямбда та ще 1
... A178: 84.2 | B178: Клуб Рослин | C178: 210/30 | D178: 11292 | E178: Пила пряма в кобурі Due Buoi RS 210/30 Італія | F178: Пила пряма в кобурі Due Buoi RS 210/30 (Дуе Буаі 210/30) | G178: 1190 | H178: 1190 | I178: назви схожі, різняться словами: буаі
A179: 84.1 | B179: Водоспад | C179: ddd10be1-abba-11ee-bf43-c87f546feb15 | D179: 32509 | E179: Окуляри захисні | F179: Окуляри захисні Estwing N6 (N6) | H179: 275 | I179: назви схожі, різняться словами: estwing
A180: 84.1 | B180: Клуб Рослин | C180: 266L | D180: 9841 | E180: Ніж для щеплення горіха Due Buoi 266L Італія | F180: Інструмент Due Buoi 266L для щеплення горіха | G180: 1725 | H180: 1725 | I180: назви схожі, різняться словами: інструмент
A181: 84.1 | B181: Клуб Рослин | C181: 3170 | D181: 14107 | E181: Фунгіцид Фундазол 200 г Сімейний Сад Україна | F181: Фунгіцид Фундазол З.П. (беноміл) 200 г Сімейний Сад | G181: 338 | H181: 350 | I181: назви схожі, різняться словами: беноміл
A182: 84.1 | B182: Клуб Рослин | C182: 88832 | D182: 12283 | E182: Скоби для садового степлера (10000 шт) Flo (88832) | F182: Скоби до степлера садового TITAN (10000 шт) | G182: 100 | H182: 99 | I182: назви схожі, але різні бренди
A183: 84 | B183: Водоспад | C183: M-TRIM-ROW | D183: 43346 | E183: Килимок для стрижки рослин в ряд з сумкою 135+140×500 см з полієстеру Oxford 350D (M-TRIM-ROW) Україна | F183: Килимок для стрижки рослин в ряд 135+140×500 см з полієстеру Oxford 350D на затяжках та кнопках (темно-зелений) з сумкою | G183: 3849 | H183: 3849 | I183: назви схожі, різняться словами: mtrimrow, затяжках, зелений та ще 2
A184: 84 | B184: Водоспад | C184: 5.107 | D184: 32337 | E184: Секатор з ковадлом Льове / Lowe Original (5.107) Німеччина | F184: Маленький секатор з ковадлом LOWE Original 5.107 (5.107) | G184: 1900 | H184: 1900 | I184: назви схожі, різняться словами: льове, маленький
A185: 84 | B185: Клуб Рослин | C185: 16.104 | D185: 11961 | E185: Секатор садовий для троянд Льове / Lowe Original (16.104) Німеччина | F185: Секатор Lowe 16.104 для троянд (Льове 16.104) | G185: 2390 | H185: 2390 | I185: назви схожі, але різні коди виробника
A186: 84 | B186: Клуб Рослин | C186: 16.107 | D186: 11962 | E186: Секатор садовий для троянд Льове / Lowe Original (16.107) Німеччина | F186: Секатор Lowe 16.107 для троянд (Льове 16.107) | G186: 2390 | H186: 2390 | I186: назви схожі, але різні коди виробника
A187: 84 | B187: Клуб Рослин | C187: 41-041 | D187: 13915 | E187: Пила садова складна Целлфаст / Cellfast ERGO 25 см 300 г (41-041) Польща | F187: Пила складна садова Cellfast Ergo 41-041 (Целфаст Ерго) | G187: 990 | H187: 1645 | I187: назви схожі, різняться словами: ерго, целлфаст, целфаст
A188: 84 | B188: Клуб Рослин | C188: 3410.B | D188: 16154 | E188: Секатор 195 мм з коваделком Bellota Smart (3410.B) Іспанія | F188: Секатор Bellota 3410 з коваделком 195 мм (Беллота 3410) | G188: 685 | H188: 685 | I188: назви схожі, але різні коди виробника
A189: 84 | B189: Клуб Рослин | C189: 8118 | D189: 14772 | E189: Добриво Агрeкол / Agrecol осіннє універсальне 0-16-20 1.2 кг Польща | F189: Добриво універсальне осіннє 3-12-24 Польща, 1 кг | G189: 352 | H189: 75 | I189: назви схожі, але різні об'єми або розміри
A190: 83.9 | B190: Клуб Рослин | C190: SR-Light | D190: 16113 | E190: Планувальник грунту ручний без держака Смарт Рейн / Smart Rain (SR-Light) Україна | F190: Планувальник грунту Smart Rain ручний 890х390 мм без держака SR-L-890 (Смарт Рейн SR-L-890) | G190: 1695 | H190: 2650 | I190: назви схожі, різняться словами: srlight
A191: 83.8 | B191: Водоспад | C191: 615/12 | D191: 32811 | E191: Щеплювальнй садовий ніж Тіна / Tina (615/12 ) Німеччина | F191: Ніж середній садовий TINA 615/12 (Німеччина) | G191: 5899 | H191: 5899 | I191: назви схожі, різняться словами: середній, тіна, щеплювальнй
... A196: 83.7 | B196: Клуб Рослин | C196: 7240 | D196: 9230 | E196: Добриво Терафлекс Баштанний Terraflex С (17-7-21 + 3 MgO + TЕ) 2 кг SmartGrow Бельгія | F196: Добриво Terraflex - C 17-7-21+3MgO+TE (Терафлекс), 2 кг | G196: 475 | H196: 371 | I196: назви схожі, різняться словами: mgo, smartgrow, баштанний
A197: 83.7 | B197: Клуб Рослин | C197: m20014 | D197: 14715 | E197: Інсектицид Актара 25 WG в.г. 6 г | F197: Інсектицид Актара 25 (тіаметоксам 250 г/кг) WG в.г. 6 г, Syngenta | H197: 66 | I197: назви схожі, різняться словами: syngenta, тіаметоксам
A198: 83.6 | B198: Водоспад | C198: 111670 | D198: 32132 | E198: Секатор із храповим механізмом Фіскарс / Fiskars PowerStep P83 (111670) Фінляндія | F198: Секатор з храповим механізмом Fiskars PowerStep Р83 (1000575) | G198: 2049 | H198: 1399 | I198: назви схожі, але різні коди виробника
A199: 83.6 | B199: Клуб Рослин | C199: 8001/В | D199: 10444 | E199: Змінне лезо для секаторів LOWE 8 (8001/В) | F199: Лезо для секатора Lowe 8 (8001) | G199: 850 | H199: 680 | I199: назви схожі, різняться словами: змінне, секаторів, секатора
A200: 83.6 | B200: Клуб Рослин | C200: 1062 | D200: 14064 | E200: Гербіцид Дабл Трай 500 мл Сімейний Сад Україна | F200: Гербіцид Дабл Трай К.Е. (метолахлор) 500 мл Сімейний Сад | G200: 575 | H200: 666 | I200: назви схожі, різняться словами: метолахлор
A201: 83.6 | B201: Клуб Рослин | C201: m1001 | D201: 16415 | E201: Гербіцид Ураган Форте 500 SL в.р.к. 300мл | F201: Гербіцид Ураган Форте 500 (калійна сіль гліфосату, 500 г/л) SL в.р.к. 300 мл, Syngenta | G201: 225 | H201: 295 | I201: назви схожі, різняться словами: syngenta, гліфосату, калійна та ще 1
A202: 83.5 | B202: Водоспад | C202: 640/10 | D202: 32808 | E202: Щеплювальний ніж Тіна / Tina (640/10) Німеччина | F202: Ніж окулювальний TINA 641/10 (Німеччина) | G202: 5699 | H202: 5999 | I202: назви схожі, різняться словами: окулювальний, тіна, щеплювальний
A203: 83.5 | B203: Водоспад | C203: 5.127 | D203: 32335 | E203: Секатор з ковадлом Льове / Lowe Original (5.127) Німеччина | F203: Секатор з ковадлом LOWE Original 2.107 (2.107) | G203: 1950 | H203: 2440 | I203: назви схожі, різняться словами: льове
A204: 83.5 | B204: Водоспад | C204: gta-SA | D204: 43389 | E204: Фартух садовий для збору врожаю та кишенями для інструментів (gta-SA) Україна | F204: Фартух садовий з кишенями для інструментів і збору врожаю, пісочного кольору, арт. gta-SA | G204: 1299 | H204: 1299 | I204: назви схожі, різняться словами: кольору, пісочного
A205: 83.5 | B205: Водоспад | C205: 2446-LAP | D205: 42600 | E205: Ніж Bahco 220 мм INOX (2446-LAP) Бахо Швеція | F205: Ніж Bahco 220 мм INOX (2446) | G205: 440 | H205: 440 | I205: назви схожі, різняться словами: бахо
A206: 83.4 | B206: Клуб Рослин | C206: 3135 | D206: 15606 | E206: Фунгіцид Мідний купорос сульфат міді 25 кг Туреччина | F206: Фунгіцид Мідний купорос (мідь сірчанокисла, сульфат міді), 1 кг | G206: 5250 | H206: 240 | I206: назви схожі, але різні об'єми або розміри
A207: 83.4 | B207: Клуб Рослин | C207: 7243 | D207: 9234 | E207: Добриво Терафлекс Квітковий Terraflex F (18-6-19 + 3 MgO + TЕ) 25 кг SmartGrow Бельгія | F207: Добриво Terraflex F 18-6-19+3MgO+TE (Терафлекс), 2 кг | G207: 4161 | H207: 374 | I207: назви схожі, але різні об'єми або розміри
A208: 83.2 | B208: Водоспад | C208: 640/10.5 | D208: 32934 | E208: Щеплювальний ніж Тіна / Tina (640/10.5 ) Німеччина | F208: Прищепний ніж TINA 640/10,5 (Німеччина) | G208: 5699 | H208: 5699 | I208: назви схожі, різняться словами: прищепний, тіна, щеплювальний
A209: 83.2 | B209: Клуб Рослин | C209: 3582.B | D209: 11053 | E209: Ножиці для обрізання кущів із загнутими ручками Bellota (3582.B) Іспанія | F209: Ножиці садові Bellota 3582.B для обрізки кущів із загнутими ручками професійні | G209: 3199 | H209: 3199 | I209: назви схожі, різняться словами: обрізання, обрізки, професійні та ще 1
... A264: 81 | B264: Клуб Рослин | C264: 7252 | D264: 9219 | E264: Добриво Плодоношення 1 л SmartGrow Україна | F264: Добриво SmartGrow ПЛОДОНОШЕННЯ, 25 мл Смарт Гроу | G264: 231 | H264: 20 | I264: назви схожі, але різні об'єми або розміри
A265: 81 | B265: Клуб Рослин | C265: 121000333202 | D265: 14594 | E265: Мастило Альпен Тамбо / Alpen Tambo (910) Швейцарія | F265: Мастило Alpen Tambo 910 синтетичне (Альпен Тамбо 910) | H265: 410 | I265: назви схожі, різняться словами: синтетичне
...

Sheet Підсумок
A1: Показник | B1: Значення | C1: Пояснення
A2: Звіт сформовано | B2: 08.10.2026 13:58
A3: Спільних товарів | B3: =COUNTA('Порівняння'!A2:A526)
A4: Потребують уваги | B4: =COUNTIF('Порівняння'!A2:A526,"Потребує уваги") | C4: червоні рядки на аркуші «Порівняння»
A5: Ваша ціна вища за орієнтир | B5: =COUNTIF('Порівняння'!A2:A526,"Ваша ціна вища")
A6: В нормі | B6: =COUNTIF('Порівняння'!A2:A526,"В нормі")
A7: Постачальник змінив ціну сьогодні | B7: =COUNT('Порівняння'!O2:O526)
A8: Немає в наявності в жодного постачальника | B8: 95 | C8: товар продається, а купити ніде
A9: Товарів у вашому фіді | B9: 3836
A10: Товарів у «Водоспад» | B10: 7072
A11: Товарів у «Клуб Рослин» | B11: 14183
A12: Пар на перевірку | B12: 2444 | C12: аркуш «Пари на перевірку»
A13: Як зіставлено | B13: код: 618, схожа назва: 35, назва: 5, модель: 16
A15: Пороги | C15: значення з config.json у репозиторії
A16: Допуск на округлення, грн | B16: 1 | C16: різниця в межах допуску не підсвічується
A17: Мінімальна націнка до ціни постачальника, % | B17: 0 | C17: нижче цього рядок червоний
A18: Максимальна націнка до ціни постачальника, % | B18: 0 | C18: вище цього рядок помаранчевий
